linkedin_search_job/__init__.py
linkedin_search_job/scraper.py
tests/__init__.py
tests/test_scraper.py
linkedin_job_search-0.1.0.dist-info/LICENSE
linkedin_job_search-0.1.0.dist-info/METADATA
linkedin_job_search-0.1.0.dist-info/WHEEL
linkedin_job_search-0.1.0.dist-info/entry_points.txt
linkedin_job_search-0.1.0.dist-info/top_level.txt
linkedin_job_search-0.1.0.dist-info/RECORD
