Metadata-Version: 2.1
Name: linkedin-job-search
Version: 0.1.0
Summary: A package Search jobs from Linkdin
Home-page: https://github.com/Tushar503/linkedin-search-job
Author: Toshar Saini
Author-email: tusharsaini503@gmail.com
Classifier: Programming Language :: Python :: 3
Classifier: License :: OSI Approved :: MIT License
Classifier: Operating System :: OS Independent
Requires-Python: >=3.6
License-File: LICENSE
Requires-Dist: requests
Requires-Dist: beautifulsoup4
